{
  "type": "File",
  "start": 0,
  "end": 702,
  "loc": {
    "start": {
      "line": 1,
      "column": 0
    },
    "end": {
      "line": 48,
      "column": 0
    }
  },
  "program": {
    "type": "Program",
    "start": 0,
    "end": 702,
    "loc": {
      "start": {
        "line": 1,
        "column": 0
      },
      "end": {
        "line": 48,
        "column": 0
      }
    },
    "sourceType": "module",
    "body": [
      {
        "type": "ExportNamedDeclaration",
        "start": 47,
        "end": 79,
        "loc": {
          "start": {
            "line": 5,
            "column": 0
          },
          "end": {
            "line": 5,
            "column": 32
          }
        },
        "specifiers": [],
        "source": null,
        "declaration": {
          "type": "VariableDeclaration",
          "start": 54,
          "end": 79,
          "loc": {
            "start": {
              "line": 5,
              "column": 7
            },
            "end": {
              "line": 5,
              "column": 32
            }
          },
          "declarations": [
            {
              "type": "VariableDeclarator",
              "start": 60,
              "end": 78,
              "loc": {
                "start": {
                  "line": 5,
                  "column": 13
                },
                "end": {
                  "line": 5,
                  "column": 31
                }
              },
              "id": {
                "type": "Identifier",
                "start": 60,
                "end": 69,
                "loc": {
                  "start": {
                    "line": 5,
                    "column": 13
                  },
                  "end": {
                    "line": 5,
                    "column": 22
                  },
                  "identifierName": "FONT_SIZE"
                },
                "name": "FONT_SIZE",
                "leadingComments": null
              },
              "init": {
                "type": "StringLiteral",
                "start": 72,
                "end": 78,
                "loc": {
                  "start": {
                    "line": 5,
                    "column": 25
                  },
                  "end": {
                    "line": 5,
                    "column": 31
                  }
                },
                "extra": {
                  "rawValue": "16px",
                  "raw": "'16px'"
                },
                "value": "16px"
              },
              "leadingComments": null
            }
          ],
          "kind": "const",
          "leadingComments": [
            {
              "type": "CommentBlock",
              "value": "*\n * Default font size\n * @type {string}\n ",
              "start": 0,
              "end": 46,
              "loc": {
                "start": {
                  "line": 1,
                  "column": 0
                },
                "end": {
                  "line": 4,
                  "column": 3
                }
              }
            }
          ],
          "trailingComments": [
            {
              "type": "CommentBlock",
              "value": "*\n * Default font family\n * @type {string}\n ",
              "start": 81,
              "end": 129,
              "loc": {
                "start": {
                  "line": 7,
                  "column": 0
                },
                "end": {
                  "line": 10,
                  "column": 3
                }
              }
            }
          ]
        },
        "leadingComments": [
          {
            "type": "CommentBlock",
            "value": "*\n * Default font size\n * @type {string}\n ",
            "start": 0,
            "end": 46,
            "loc": {
              "start": {
                "line": 1,
                "column": 0
              },
              "end": {
                "line": 4,
                "column": 3
              }
            }
          }
        ],
        "trailingComments": [
          {
            "type": "CommentBlock",
            "value": "*\n * Default font family\n * @type {string}\n ",
            "start": 81,
            "end": 129,
            "loc": {
              "start": {
                "line": 7,
                "column": 0
              },
              "end": {
                "line": 10,
                "column": 3
              }
            }
          }
        ]
      },
      {
        "type": "ExportNamedDeclaration",
        "start": 130,
        "end": 170,
        "loc": {
          "start": {
            "line": 11,
            "column": 0
          },
          "end": {
            "line": 11,
            "column": 40
          }
        },
        "specifiers": [],
        "source": null,
        "declaration": {
          "type": "VariableDeclaration",
          "start": 137,
          "end": 170,
          "loc": {
            "start": {
              "line": 11,
              "column": 7
            },
            "end": {
              "line": 11,
              "column": 40
            }
          },
          "declarations": [
            {
              "type": "VariableDeclarator",
              "start": 143,
              "end": 169,
              "loc": {
                "start": {
                  "line": 11,
                  "column": 13
                },
                "end": {
                  "line": 11,
                  "column": 39
                }
              },
              "id": {
                "type": "Identifier",
                "start": 143,
                "end": 154,
                "loc": {
                  "start": {
                    "line": 11,
                    "column": 13
                  },
                  "end": {
                    "line": 11,
                    "column": 24
                  },
                  "identifierName": "FONT_FAMILY"
                },
                "name": "FONT_FAMILY",
                "leadingComments": null
              },
              "init": {
                "type": "StringLiteral",
                "start": 157,
                "end": 169,
                "loc": {
                  "start": {
                    "line": 11,
                    "column": 27
                  },
                  "end": {
                    "line": 11,
                    "column": 39
                  }
                },
                "extra": {
                  "rawValue": "sans-serif",
                  "raw": "'sans-serif'"
                },
                "value": "sans-serif"
              },
              "leadingComments": null
            }
          ],
          "kind": "const",
          "leadingComments": [
            {
              "type": "CommentBlock",
              "value": "*\n * Default font family\n * @type {string}\n ",
              "start": 81,
              "end": 129,
              "loc": {
                "start": {
                  "line": 7,
                  "column": 0
                },
                "end": {
                  "line": 10,
                  "column": 3
                }
              }
            }
          ],
          "trailingComments": [
            {
              "type": "CommentBlock",
              "value": "*\n * Default font style\n * @type {string}\n ",
              "start": 172,
              "end": 219,
              "loc": {
                "start": {
                  "line": 13,
                  "column": 0
                },
                "end": {
                  "line": 16,
                  "column": 3
                }
              }
            }
          ]
        },
        "leadingComments": [
          {
            "type": "CommentBlock",
            "value": "*\n * Default font family\n * @type {string}\n ",
            "start": 81,
            "end": 129,
            "loc": {
              "start": {
                "line": 7,
                "column": 0
              },
              "end": {
                "line": 10,
                "column": 3
              }
            }
          }
        ],
        "trailingComments": [
          {
            "type": "CommentBlock",
            "value": "*\n * Default font style\n * @type {string}\n ",
            "start": 172,
            "end": 219,
            "loc": {
              "start": {
                "line": 13,
                "column": 0
              },
              "end": {
                "line": 16,
                "column": 3
              }
            }
          }
        ]
      },
      {
        "type": "ExportNamedDeclaration",
        "start": 220,
        "end": 255,
        "loc": {
          "start": {
            "line": 17,
            "column": 0
          },
          "end": {
            "line": 17,
            "column": 35
          }
        },
        "specifiers": [],
        "source": null,
        "declaration": {
          "type": "VariableDeclaration",
          "start": 227,
          "end": 255,
          "loc": {
            "start": {
              "line": 17,
              "column": 7
            },
            "end": {
              "line": 17,
              "column": 35
            }
          },
          "declarations": [
            {
              "type": "VariableDeclarator",
              "start": 233,
              "end": 254,
              "loc": {
                "start": {
                  "line": 17,
                  "column": 13
                },
                "end": {
                  "line": 17,
                  "column": 34
                }
              },
              "id": {
                "type": "Identifier",
                "start": 233,
                "end": 243,
                "loc": {
                  "start": {
                    "line": 17,
                    "column": 13
                  },
                  "end": {
                    "line": 17,
                    "column": 23
                  },
                  "identifierName": "FONT_STYLE"
                },
                "name": "FONT_STYLE",
                "leadingComments": null
              },
              "init": {
                "type": "StringLiteral",
                "start": 246,
                "end": 254,
                "loc": {
                  "start": {
                    "line": 17,
                    "column": 26
                  },
                  "end": {
                    "line": 17,
                    "column": 34
                  }
                },
                "extra": {
                  "rawValue": "normal",
                  "raw": "'normal'"
                },
                "value": "normal"
              },
              "leadingComments": null
            }
          ],
          "kind": "const",
          "leadingComments": [
            {
              "type": "CommentBlock",
              "value": "*\n * Default font style\n * @type {string}\n ",
              "start": 172,
              "end": 219,
              "loc": {
                "start": {
                  "line": 13,
                  "column": 0
                },
                "end": {
                  "line": 16,
                  "column": 3
                }
              }
            }
          ],
          "trailingComments": [
            {
              "type": "CommentBlock",
              "value": "*\n * Default font variant\n * @type {string}\n ",
              "start": 257,
              "end": 306,
              "loc": {
                "start": {
                  "line": 19,
                  "column": 0
                },
                "end": {
                  "line": 22,
                  "column": 3
                }
              }
            }
          ]
        },
        "leadingComments": [
          {
            "type": "CommentBlock",
            "value": "*\n * Default font style\n * @type {string}\n ",
            "start": 172,
            "end": 219,
            "loc": {
              "start": {
                "line": 13,
                "column": 0
              },
              "end": {
                "line": 16,
                "column": 3
              }
            }
          }
        ],
        "trailingComments": [
          {
            "type": "CommentBlock",
            "value": "*\n * Default font variant\n * @type {string}\n ",
            "start": 257,
            "end": 306,
            "loc": {
              "start": {
                "line": 19,
                "column": 0
              },
              "end": {
                "line": 22,
                "column": 3
              }
            }
          }
        ]
      },
      {
        "type": "ExportNamedDeclaration",
        "start": 307,
        "end": 344,
        "loc": {
          "start": {
            "line": 23,
            "column": 0
          },
          "end": {
            "line": 23,
            "column": 37
          }
        },
        "specifiers": [],
        "source": null,
        "declaration": {
          "type": "VariableDeclaration",
          "start": 314,
          "end": 344,
          "loc": {
            "start": {
              "line": 23,
              "column": 7
            },
            "end": {
              "line": 23,
              "column": 37
            }
          },
          "declarations": [
            {
              "type": "VariableDeclarator",
              "start": 320,
              "end": 343,
              "loc": {
                "start": {
                  "line": 23,
                  "column": 13
                },
                "end": {
                  "line": 23,
                  "column": 36
                }
              },
              "id": {
                "type": "Identifier",
                "start": 320,
                "end": 332,
                "loc": {
                  "start": {
                    "line": 23,
                    "column": 13
                  },
                  "end": {
                    "line": 23,
                    "column": 25
                  },
                  "identifierName": "FONT_VARIANT"
                },
                "name": "FONT_VARIANT",
                "leadingComments": null
              },
              "init": {
                "type": "StringLiteral",
                "start": 335,
                "end": 343,
                "loc": {
                  "start": {
                    "line": 23,
                    "column": 28
                  },
                  "end": {
                    "line": 23,
                    "column": 36
                  }
                },
                "extra": {
                  "rawValue": "normal",
                  "raw": "'normal'"
                },
                "value": "normal"
              },
              "leadingComments": null
            }
          ],
          "kind": "const",
          "leadingComments": [
            {
              "type": "CommentBlock",
              "value": "*\n * Default font variant\n * @type {string}\n ",
              "start": 257,
              "end": 306,
              "loc": {
                "start": {
                  "line": 19,
                  "column": 0
                },
                "end": {
                  "line": 22,
                  "column": 3
                }
              }
            }
          ],
          "trailingComments": [
            {
              "type": "CommentBlock",
              "value": "*\n * Default font weight\n * @type {string}\n ",
              "start": 346,
              "end": 394,
              "loc": {
                "start": {
                  "line": 25,
                  "column": 0
                },
                "end": {
                  "line": 28,
                  "column": 3
                }
              }
            }
          ]
        },
        "leadingComments": [
          {
            "type": "CommentBlock",
            "value": "*\n * Default font variant\n * @type {string}\n ",
            "start": 257,
            "end": 306,
            "loc": {
              "start": {
                "line": 19,
                "column": 0
              },
              "end": {
                "line": 22,
                "column": 3
              }
            }
          }
        ],
        "trailingComments": [
          {
            "type": "CommentBlock",
            "value": "*\n * Default font weight\n * @type {string}\n ",
            "start": 346,
            "end": 394,
            "loc": {
              "start": {
                "line": 25,
                "column": 0
              },
              "end": {
                "line": 28,
                "column": 3
              }
            }
          }
        ]
      },
      {
        "type": "ExportNamedDeclaration",
        "start": 395,
        "end": 431,
        "loc": {
          "start": {
            "line": 29,
            "column": 0
          },
          "end": {
            "line": 29,
            "column": 36
          }
        },
        "specifiers": [],
        "source": null,
        "declaration": {
          "type": "VariableDeclaration",
          "start": 402,
          "end": 431,
          "loc": {
            "start": {
              "line": 29,
              "column": 7
            },
            "end": {
              "line": 29,
              "column": 36
            }
          },
          "declarations": [
            {
              "type": "VariableDeclarator",
              "start": 408,
              "end": 430,
              "loc": {
                "start": {
                  "line": 29,
                  "column": 13
                },
                "end": {
                  "line": 29,
                  "column": 35
                }
              },
              "id": {
                "type": "Identifier",
                "start": 408,
                "end": 419,
                "loc": {
                  "start": {
                    "line": 29,
                    "column": 13
                  },
                  "end": {
                    "line": 29,
                    "column": 24
                  },
                  "identifierName": "FONT_WEIGHT"
                },
                "name": "FONT_WEIGHT",
                "leadingComments": null
              },
              "init": {
                "type": "StringLiteral",
                "start": 422,
                "end": 430,
                "loc": {
                  "start": {
                    "line": 29,
                    "column": 27
                  },
                  "end": {
                    "line": 29,
                    "column": 35
                  }
                },
                "extra": {
                  "rawValue": "normal",
                  "raw": "'normal'"
                },
                "value": "normal"
              },
              "leadingComments": null
            }
          ],
          "kind": "const",
          "leadingComments": [
            {
              "type": "CommentBlock",
              "value": "*\n * Default font weight\n * @type {string}\n ",
              "start": 346,
              "end": 394,
              "loc": {
                "start": {
                  "line": 25,
                  "column": 0
                },
                "end": {
                  "line": 28,
                  "column": 3
                }
              }
            }
          ],
          "trailingComments": [
            {
              "type": "CommentBlock",
              "value": "*\n * Default line height\n * @type {string}\n ",
              "start": 433,
              "end": 481,
              "loc": {
                "start": {
                  "line": 31,
                  "column": 0
                },
                "end": {
                  "line": 34,
                  "column": 3
                }
              }
            }
          ]
        },
        "leadingComments": [
          {
            "type": "CommentBlock",
            "value": "*\n * Default font weight\n * @type {string}\n ",
            "start": 346,
            "end": 394,
            "loc": {
              "start": {
                "line": 25,
                "column": 0
              },
              "end": {
                "line": 28,
                "column": 3
              }
            }
          }
        ],
        "trailingComments": [
          {
            "type": "CommentBlock",
            "value": "*\n * Default line height\n * @type {string}\n ",
            "start": 433,
            "end": 481,
            "loc": {
              "start": {
                "line": 31,
                "column": 0
              },
              "end": {
                "line": 34,
                "column": 3
              }
            }
          }
        ]
      },
      {
        "type": "ExportNamedDeclaration",
        "start": 482,
        "end": 518,
        "loc": {
          "start": {
            "line": 35,
            "column": 0
          },
          "end": {
            "line": 35,
            "column": 36
          }
        },
        "specifiers": [],
        "source": null,
        "declaration": {
          "type": "VariableDeclaration",
          "start": 489,
          "end": 518,
          "loc": {
            "start": {
              "line": 35,
              "column": 7
            },
            "end": {
              "line": 35,
              "column": 36
            }
          },
          "declarations": [
            {
              "type": "VariableDeclarator",
              "start": 495,
              "end": 517,
              "loc": {
                "start": {
                  "line": 35,
                  "column": 13
                },
                "end": {
                  "line": 35,
                  "column": 35
                }
              },
              "id": {
                "type": "Identifier",
                "start": 495,
                "end": 506,
                "loc": {
                  "start": {
                    "line": 35,
                    "column": 13
                  },
                  "end": {
                    "line": 35,
                    "column": 24
                  },
                  "identifierName": "LINE_HEIGHT"
                },
                "name": "LINE_HEIGHT",
                "leadingComments": null
              },
              "init": {
                "type": "StringLiteral",
                "start": 509,
                "end": 517,
                "loc": {
                  "start": {
                    "line": 35,
                    "column": 27
                  },
                  "end": {
                    "line": 35,
                    "column": 35
                  }
                },
                "extra": {
                  "rawValue": "normal",
                  "raw": "'normal'"
                },
                "value": "normal"
              },
              "leadingComments": null
            }
          ],
          "kind": "const",
          "leadingComments": [
            {
              "type": "CommentBlock",
              "value": "*\n * Default line height\n * @type {string}\n ",
              "start": 433,
              "end": 481,
              "loc": {
                "start": {
                  "line": 31,
                  "column": 0
                },
                "end": {
                  "line": 34,
                  "column": 3
                }
              }
            }
          ],
          "trailingComments": [
            {
              "type": "CommentBlock",
              "value": "*\n * Default text alignment\n * @type {string}\n ",
              "start": 520,
              "end": 571,
              "loc": {
                "start": {
                  "line": 37,
                  "column": 0
                },
                "end": {
                  "line": 40,
                  "column": 3
                }
              }
            }
          ]
        },
        "leadingComments": [
          {
            "type": "CommentBlock",
            "value": "*\n * Default line height\n * @type {string}\n ",
            "start": 433,
            "end": 481,
            "loc": {
              "start": {
                "line": 31,
                "column": 0
              },
              "end": {
                "line": 34,
                "column": 3
              }
            }
          }
        ],
        "trailingComments": [
          {
            "type": "CommentBlock",
            "value": "*\n * Default text alignment\n * @type {string}\n ",
            "start": 520,
            "end": 571,
            "loc": {
              "start": {
                "line": 37,
                "column": 0
              },
              "end": {
                "line": 40,
                "column": 3
              }
            }
          }
        ]
      },
      {
        "type": "ExportNamedDeclaration",
        "start": 572,
        "end": 606,
        "loc": {
          "start": {
            "line": 41,
            "column": 0
          },
          "end": {
            "line": 41,
            "column": 34
          }
        },
        "specifiers": [],
        "source": null,
        "declaration": {
          "type": "VariableDeclaration",
          "start": 579,
          "end": 606,
          "loc": {
            "start": {
              "line": 41,
              "column": 7
            },
            "end": {
              "line": 41,
              "column": 34
            }
          },
          "declarations": [
            {
              "type": "VariableDeclarator",
              "start": 585,
              "end": 605,
              "loc": {
                "start": {
                  "line": 41,
                  "column": 13
                },
                "end": {
                  "line": 41,
                  "column": 33
                }
              },
              "id": {
                "type": "Identifier",
                "start": 585,
                "end": 595,
                "loc": {
                  "start": {
                    "line": 41,
                    "column": 13
                  },
                  "end": {
                    "line": 41,
                    "column": 23
                  },
                  "identifierName": "TEXT_ALIGN"
                },
                "name": "TEXT_ALIGN",
                "leadingComments": null
              },
              "init": {
                "type": "StringLiteral",
                "start": 598,
                "end": 605,
                "loc": {
                  "start": {
                    "line": 41,
                    "column": 26
                  },
                  "end": {
                    "line": 41,
                    "column": 33
                  }
                },
                "extra": {
                  "rawValue": "start",
                  "raw": "'start'"
                },
                "value": "start"
              },
              "leadingComments": null
            }
          ],
          "kind": "const",
          "leadingComments": [
            {
              "type": "CommentBlock",
              "value": "*\n * Default text alignment\n * @type {string}\n ",
              "start": 520,
              "end": 571,
              "loc": {
                "start": {
                  "line": 37,
                  "column": 0
                },
                "end": {
                  "line": 40,
                  "column": 3
                }
              }
            }
          ],
          "trailingComments": [
            {
              "type": "CommentBlock",
              "value": "*\n * Default text baseline\n * @type {string}\n ",
              "start": 608,
              "end": 658,
              "loc": {
                "start": {
                  "line": 43,
                  "column": 0
                },
                "end": {
                  "line": 46,
                  "column": 3
                }
              }
            }
          ]
        },
        "leadingComments": [
          {
            "type": "CommentBlock",
            "value": "*\n * Default text alignment\n * @type {string}\n ",
            "start": 520,
            "end": 571,
            "loc": {
              "start": {
                "line": 37,
                "column": 0
              },
              "end": {
                "line": 40,
                "column": 3
              }
            }
          }
        ],
        "trailingComments": [
          {
            "type": "CommentBlock",
            "value": "*\n * Default text baseline\n * @type {string}\n ",
            "start": 608,
            "end": 658,
            "loc": {
              "start": {
                "line": 43,
                "column": 0
              },
              "end": {
                "line": 46,
                "column": 3
              }
            }
          }
        ]
      },
      {
        "type": "ExportNamedDeclaration",
        "start": 659,
        "end": 701,
        "loc": {
          "start": {
            "line": 47,
            "column": 0
          },
          "end": {
            "line": 47,
            "column": 42
          }
        },
        "specifiers": [],
        "source": null,
        "declaration": {
          "type": "VariableDeclaration",
          "start": 666,
          "end": 701,
          "loc": {
            "start": {
              "line": 47,
              "column": 7
            },
            "end": {
              "line": 47,
              "column": 42
            }
          },
          "declarations": [
            {
              "type": "VariableDeclarator",
              "start": 672,
              "end": 700,
              "loc": {
                "start": {
                  "line": 47,
                  "column": 13
                },
                "end": {
                  "line": 47,
                  "column": 41
                }
              },
              "id": {
                "type": "Identifier",
                "start": 672,
                "end": 685,
                "loc": {
                  "start": {
                    "line": 47,
                    "column": 13
                  },
                  "end": {
                    "line": 47,
                    "column": 26
                  },
                  "identifierName": "TEXT_BASELINE"
                },
                "name": "TEXT_BASELINE",
                "leadingComments": null
              },
              "init": {
                "type": "StringLiteral",
                "start": 688,
                "end": 700,
                "loc": {
                  "start": {
                    "line": 47,
                    "column": 29
                  },
                  "end": {
                    "line": 47,
                    "column": 41
                  }
                },
                "extra": {
                  "rawValue": "alphabetic",
                  "raw": "'alphabetic'"
                },
                "value": "alphabetic"
              },
              "leadingComments": null
            }
          ],
          "kind": "const",
          "leadingComments": [
            {
              "type": "CommentBlock",
              "value": "*\n * Default text baseline\n * @type {string}\n ",
              "start": 608,
              "end": 658,
              "loc": {
                "start": {
                  "line": 43,
                  "column": 0
                },
                "end": {
                  "line": 46,
                  "column": 3
                }
              }
            }
          ],
          "trailingComments": []
        },
        "leadingComments": [
          {
            "type": "CommentBlock",
            "value": "*\n * Default text baseline\n * @type {string}\n ",
            "start": 608,
            "end": 658,
            "loc": {
              "start": {
                "line": 43,
                "column": 0
              },
              "end": {
                "line": 46,
                "column": 3
              }
            }
          }
        ]
      }
    ],
    "directives": []
  },
  "comments": [
    {
      "type": "CommentBlock",
      "value": "*\n * Default font size\n * @type {string}\n ",
      "start": 0,
      "end": 46,
      "loc": {
        "start": {
          "line": 1,
          "column": 0
        },
        "end": {
          "line": 4,
          "column": 3
        }
      }
    },
    {
      "type": "CommentBlock",
      "value": "*\n * Default font family\n * @type {string}\n ",
      "start": 81,
      "end": 129,
      "loc": {
        "start": {
          "line": 7,
          "column": 0
        },
        "end": {
          "line": 10,
          "column": 3
        }
      }
    },
    {
      "type": "CommentBlock",
      "value": "*\n * Default font style\n * @type {string}\n ",
      "start": 172,
      "end": 219,
      "loc": {
        "start": {
          "line": 13,
          "column": 0
        },
        "end": {
          "line": 16,
          "column": 3
        }
      }
    },
    {
      "type": "CommentBlock",
      "value": "*\n * Default font variant\n * @type {string}\n ",
      "start": 257,
      "end": 306,
      "loc": {
        "start": {
          "line": 19,
          "column": 0
        },
        "end": {
          "line": 22,
          "column": 3
        }
      }
    },
    {
      "type": "CommentBlock",
      "value": "*\n * Default font weight\n * @type {string}\n ",
      "start": 346,
      "end": 394,
      "loc": {
        "start": {
          "line": 25,
          "column": 0
        },
        "end": {
          "line": 28,
          "column": 3
        }
      }
    },
    {
      "type": "CommentBlock",
      "value": "*\n * Default line height\n * @type {string}\n ",
      "start": 433,
      "end": 481,
      "loc": {
        "start": {
          "line": 31,
          "column": 0
        },
        "end": {
          "line": 34,
          "column": 3
        }
      }
    },
    {
      "type": "CommentBlock",
      "value": "*\n * Default text alignment\n * @type {string}\n ",
      "start": 520,
      "end": 571,
      "loc": {
        "start": {
          "line": 37,
          "column": 0
        },
        "end": {
          "line": 40,
          "column": 3
        }
      }
    },
    {
      "type": "CommentBlock",
      "value": "*\n * Default text baseline\n * @type {string}\n ",
      "start": 608,
      "end": 658,
      "loc": {
        "start": {
          "line": 43,
          "column": 0
        },
        "end": {
          "line": 46,
          "column": 3
        }
      }
    }
  ],
  "tokens": [
    {
      "type": "CommentBlock",
      "value": "*\n * Default font size\n * @type {string}\n ",
      "start": 0,
      "end": 46,
      "loc": {
        "start": {
          "line": 1,
          "column": 0
        },
        "end": {
          "line": 4,
          "column": 3
        }
      }
    },
    {
      "type": {
        "label": "export",
        "keyword": "export",
        "beforeExpr": false,
        "startsExpr": false,
        "rightAssociative": false,
        "isLoop": false,
        "isAssign": false,
        "prefix": false,
        "postfix": false,
        "binop": null,
        "updateContext": null
      },
      "value": "export",
      "start": 47,
      "end": 53,
      "loc": {
        "start": {
          "line": 5,
          "column": 0
        },
        "end": {
          "line": 5,
          "column": 6
        }
      }
    },
    {
      "type": {
        "label": "const",
        "keyword": "const",
        "beforeExpr": false,
        "startsExpr": false,
        "rightAssociative": false,
        "isLoop": false,
        "isAssign": false,
        "prefix": false,
        "postfix": false,
        "binop": null,
        "updateContext": null
      },
      "value": "const",
      "start": 54,
      "end": 59,
      "loc": {
        "start": {
          "line": 5,
          "column": 7
        },
        "end": {
          "line": 5,
          "column": 12
        }
      }
    },
    {
      "type": {
        "label": "name",
        "beforeExpr": false,
        "startsExpr": true,
        "rightAssociative": false,
        "isLoop": false,
        "isAssign": false,
        "prefix": false,
        "postfix": false,
        "binop": null
      },
      "value": "FONT_SIZE",
      "start": 60,
      "end": 69,
      "loc": {
        "start": {
          "line": 5,
          "column": 13
        },
        "end": {
          "line": 5,
          "column": 22
        }
      }
    },
    {
      "type": {
        "label": "=",
        "beforeExpr": true,
        "startsExpr": false,
        "rightAssociative": false,
        "isLoop": false,
        "isAssign": true,
        "prefix": false,
        "postfix": false,
        "binop": null,
        "updateContext": null
      },
      "value": "=",
      "start": 70,
      "end": 71,
      "loc": {
        "start": {
          "line": 5,
          "column": 23
        },
        "end": {
          "line": 5,
          "column": 24
        }
      }
    },
    {
      "type": {
        "label": "string",
        "beforeExpr": false,
        "startsExpr": true,
        "rightAssociative": false,
        "isLoop": false,
        "isAssign": false,
        "prefix": false,
        "postfix": false,
        "binop": null,
        "updateContext": null
      },
      "value": "16px",
      "start": 72,
      "end": 78,
      "loc": {
        "start": {
          "line": 5,
          "column": 25
        },
        "end": {
          "line": 5,
          "column": 31
        }
      }
    },
    {
      "type": {
        "label": ";",
        "beforeExpr": true,
        "startsExpr": false,
        "rightAssociative": false,
        "isLoop": false,
        "isAssign": false,
        "prefix": false,
        "postfix": false,
        "binop": null,
        "updateContext": null
      },
      "start": 78,
      "end": 79,
      "loc": {
        "start": {
          "line": 5,
          "column": 31
        },
        "end": {
          "line": 5,
          "column": 32
        }
      }
    },
    {
      "type": "CommentBlock",
      "value": "*\n * Default font family\n * @type {string}\n ",
      "start": 81,
      "end": 129,
      "loc": {
        "start": {
          "line": 7,
          "column": 0
        },
        "end": {
          "line": 10,
          "column": 3
        }
      }
    },
    {
      "type": {
        "label": "export",
        "keyword": "export",
        "beforeExpr": false,
        "startsExpr": false,
        "rightAssociative": false,
        "isLoop": false,
        "isAssign": false,
        "prefix": false,
        "postfix": false,
        "binop": null,
        "updateContext": null
      },
      "value": "export",
      "start": 130,
      "end": 136,
      "loc": {
        "start": {
          "line": 11,
          "column": 0
        },
        "end": {
          "line": 11,
          "column": 6
        }
      }
    },
    {
      "type": {
        "label": "const",
        "keyword": "const",
        "beforeExpr": false,
        "startsExpr": false,
        "rightAssociative": false,
        "isLoop": false,
        "isAssign": false,
        "prefix": false,
        "postfix": false,
        "binop": null,
        "updateContext": null
      },
      "value": "const",
      "start": 137,
      "end": 142,
      "loc": {
        "start": {
          "line": 11,
          "column": 7
        },
        "end": {
          "line": 11,
          "column": 12
        }
      }
    },
    {
      "type": {
        "label": "name",
        "beforeExpr": false,
        "startsExpr": true,
        "rightAssociative": false,
        "isLoop": false,
        "isAssign": false,
        "prefix": false,
        "postfix": false,
        "binop": null
      },
      "value": "FONT_FAMILY",
      "start": 143,
      "end": 154,
      "loc": {
        "start": {
          "line": 11,
          "column": 13
        },
        "end": {
          "line": 11,
          "column": 24
        }
      }
    },
    {
      "type": {
        "label": "=",
        "beforeExpr": true,
        "startsExpr": false,
        "rightAssociative": false,
        "isLoop": false,
        "isAssign": true,
        "prefix": false,
        "postfix": false,
        "binop": null,
        "updateContext": null
      },
      "value": "=",
      "start": 155,
      "end": 156,
      "loc": {
        "start": {
          "line": 11,
          "column": 25
        },
        "end": {
          "line": 11,
          "column": 26
        }
      }
    },
    {
      "type": {
        "label": "string",
        "beforeExpr": false,
        "startsExpr": true,
        "rightAssociative": false,
        "isLoop": false,
        "isAssign": false,
        "prefix": false,
        "postfix": false,
        "binop": null,
        "updateContext": null
      },
      "value": "sans-serif",
      "start": 157,
      "end": 169,
      "loc": {
        "start": {
          "line": 11,
          "column": 27
        },
        "end": {
          "line": 11,
          "column": 39
        }
      }
    },
    {
      "type": {
        "label": ";",
        "beforeExpr": true,
        "startsExpr": false,
        "rightAssociative": false,
        "isLoop": false,
        "isAssign": false,
        "prefix": false,
        "postfix": false,
        "binop": null,
        "updateContext": null
      },
      "start": 169,
      "end": 170,
      "loc": {
        "start": {
          "line": 11,
          "column": 39
        },
        "end": {
          "line": 11,
          "column": 40
        }
      }
    },
    {
      "type": "CommentBlock",
      "value": "*\n * Default font style\n * @type {string}\n ",
      "start": 172,
      "end": 219,
      "loc": {
        "start": {
          "line": 13,
          "column": 0
        },
        "end": {
          "line": 16,
          "column": 3
        }
      }
    },
    {
      "type": {
        "label": "export",
        "keyword": "export",
        "beforeExpr": false,
        "startsExpr": false,
        "rightAssociative": false,
        "isLoop": false,
        "isAssign": false,
        "prefix": false,
        "postfix": false,
        "binop": null,
        "updateContext": null
      },
      "value": "export",
      "start": 220,
      "end": 226,
      "loc": {
        "start": {
          "line": 17,
          "column": 0
        },
        "end": {
          "line": 17,
          "column": 6
        }
      }
    },
    {
      "type": {
        "label": "const",
        "keyword": "const",
        "beforeExpr": false,
        "startsExpr": false,
        "rightAssociative": false,
        "isLoop": false,
        "isAssign": false,
        "prefix": false,
        "postfix": false,
        "binop": null,
        "updateContext": null
      },
      "value": "const",
      "start": 227,
      "end": 232,
      "loc": {
        "start": {
          "line": 17,
          "column": 7
        },
        "end": {
          "line": 17,
          "column": 12
        }
      }
    },
    {
      "type": {
        "label": "name",
        "beforeExpr": false,
        "startsExpr": true,
        "rightAssociative": false,
        "isLoop": false,
        "isAssign": false,
        "prefix": false,
        "postfix": false,
        "binop": null
      },
      "value": "FONT_STYLE",
      "start": 233,
      "end": 243,
      "loc": {
        "start": {
          "line": 17,
          "column": 13
        },
        "end": {
          "line": 17,
          "column": 23
        }
      }
    },
    {
      "type": {
        "label": "=",
        "beforeExpr": true,
        "startsExpr": false,
        "rightAssociative": false,
        "isLoop": false,
        "isAssign": true,
        "prefix": false,
        "postfix": false,
        "binop": null,
        "updateContext": null
      },
      "value": "=",
      "start": 244,
      "end": 245,
      "loc": {
        "start": {
          "line": 17,
          "column": 24
        },
        "end": {
          "line": 17,
          "column": 25
        }
      }
    },
    {
      "type": {
        "label": "string",
        "beforeExpr": false,
        "startsExpr": true,
        "rightAssociative": false,
        "isLoop": false,
        "isAssign": false,
        "prefix": false,
        "postfix": false,
        "binop": null,
        "updateContext": null
      },
      "value": "normal",
      "start": 246,
      "end": 254,
      "loc": {
        "start": {
          "line": 17,
          "column": 26
        },
        "end": {
          "line": 17,
          "column": 34
        }
      }
    },
    {
      "type": {
        "label": ";",
        "beforeExpr": true,
        "startsExpr": false,
        "rightAssociative": false,
        "isLoop": false,
        "isAssign": false,
        "prefix": false,
        "postfix": false,
        "binop": null,
        "updateContext": null
      },
      "start": 254,
      "end": 255,
      "loc": {
        "start": {
          "line": 17,
          "column": 34
        },
        "end": {
          "line": 17,
          "column": 35
        }
      }
    },
    {
      "type": "CommentBlock",
      "value": "*\n * Default font variant\n * @type {string}\n ",
      "start": 257,
      "end": 306,
      "loc": {
        "start": {
          "line": 19,
          "column": 0
        },
        "end": {
          "line": 22,
          "column": 3
        }
      }
    },
    {
      "type": {
        "label": "export",
        "keyword": "export",
        "beforeExpr": false,
        "startsExpr": false,
        "rightAssociative": false,
        "isLoop": false,
        "isAssign": false,
        "prefix": false,
        "postfix": false,
        "binop": null,
        "updateContext": null
      },
      "value": "export",
      "start": 307,
      "end": 313,
      "loc": {
        "start": {
          "line": 23,
          "column": 0
        },
        "end": {
          "line": 23,
          "column": 6
        }
      }
    },
    {
      "type": {
        "label": "const",
        "keyword": "const",
        "beforeExpr": false,
        "startsExpr": false,
        "rightAssociative": false,
        "isLoop": false,
        "isAssign": false,
        "prefix": false,
        "postfix": false,
        "binop": null,
        "updateContext": null
      },
      "value": "const",
      "start": 314,
      "end": 319,
      "loc": {
        "start": {
          "line": 23,
          "column": 7
        },
        "end": {
          "line": 23,
          "column": 12
        }
      }
    },
    {
      "type": {
        "label": "name",
        "beforeExpr": false,
        "startsExpr": true,
        "rightAssociative": false,
        "isLoop": false,
        "isAssign": false,
        "prefix": false,
        "postfix": false,
        "binop": null
      },
      "value": "FONT_VARIANT",
      "start": 320,
      "end": 332,
      "loc": {
        "start": {
          "line": 23,
          "column": 13
        },
        "end": {
          "line": 23,
          "column": 25
        }
      }
    },
    {
      "type": {
        "label": "=",
        "beforeExpr": true,
        "startsExpr": false,
        "rightAssociative": false,
        "isLoop": false,
        "isAssign": true,
        "prefix": false,
        "postfix": false,
        "binop": null,
        "updateContext": null
      },
      "value": "=",
      "start": 333,
      "end": 334,
      "loc": {
        "start": {
          "line": 23,
          "column": 26
        },
        "end": {
          "line": 23,
          "column": 27
        }
      }
    },
    {
      "type": {
        "label": "string",
        "beforeExpr": false,
        "startsExpr": true,
        "rightAssociative": false,
        "isLoop": false,
        "isAssign": false,
        "prefix": false,
        "postfix": false,
        "binop": null,
        "updateContext": null
      },
      "value": "normal",
      "start": 335,
      "end": 343,
      "loc": {
        "start": {
          "line": 23,
          "column": 28
        },
        "end": {
          "line": 23,
          "column": 36
        }
      }
    },
    {
      "type": {
        "label": ";",
        "beforeExpr": true,
        "startsExpr": false,
        "rightAssociative": false,
        "isLoop": false,
        "isAssign": false,
        "prefix": false,
        "postfix": false,
        "binop": null,
        "updateContext": null
      },
      "start": 343,
      "end": 344,
      "loc": {
        "start": {
          "line": 23,
          "column": 36
        },
        "end": {
          "line": 23,
          "column": 37
        }
      }
    },
    {
      "type": "CommentBlock",
      "value": "*\n * Default font weight\n * @type {string}\n ",
      "start": 346,
      "end": 394,
      "loc": {
        "start": {
          "line": 25,
          "column": 0
        },
        "end": {
          "line": 28,
          "column": 3
        }
      }
    },
    {
      "type": {
        "label": "export",
        "keyword": "export",
        "beforeExpr": false,
        "startsExpr": false,
        "rightAssociative": false,
        "isLoop": false,
        "isAssign": false,
        "prefix": false,
        "postfix": false,
        "binop": null,
        "updateContext": null
      },
      "value": "export",
      "start": 395,
      "end": 401,
      "loc": {
        "start": {
          "line": 29,
          "column": 0
        },
        "end": {
          "line": 29,
          "column": 6
        }
      }
    },
    {
      "type": {
        "label": "const",
        "keyword": "const",
        "beforeExpr": false,
        "startsExpr": false,
        "rightAssociative": false,
        "isLoop": false,
        "isAssign": false,
        "prefix": false,
        "postfix": false,
        "binop": null,
        "updateContext": null
      },
      "value": "const",
      "start": 402,
      "end": 407,
      "loc": {
        "start": {
          "line": 29,
          "column": 7
        },
        "end": {
          "line": 29,
          "column": 12
        }
      }
    },
    {
      "type": {
        "label": "name",
        "beforeExpr": false,
        "startsExpr": true,
        "rightAssociative": false,
        "isLoop": false,
        "isAssign": false,
        "prefix": false,
        "postfix": false,
        "binop": null
      },
      "value": "FONT_WEIGHT",
      "start": 408,
      "end": 419,
      "loc": {
        "start": {
          "line": 29,
          "column": 13
        },
        "end": {
          "line": 29,
          "column": 24
        }
      }
    },
    {
      "type": {
        "label": "=",
        "beforeExpr": true,
        "startsExpr": false,
        "rightAssociative": false,
        "isLoop": false,
        "isAssign": true,
        "prefix": false,
        "postfix": false,
        "binop": null,
        "updateContext": null
      },
      "value": "=",
      "start": 420,
      "end": 421,
      "loc": {
        "start": {
          "line": 29,
          "column": 25
        },
        "end": {
          "line": 29,
          "column": 26
        }
      }
    },
    {
      "type": {
        "label": "string",
        "beforeExpr": false,
        "startsExpr": true,
        "rightAssociative": false,
        "isLoop": false,
        "isAssign": false,
        "prefix": false,
        "postfix": false,
        "binop": null,
        "updateContext": null
      },
      "value": "normal",
      "start": 422,
      "end": 430,
      "loc": {
        "start": {
          "line": 29,
          "column": 27
        },
        "end": {
          "line": 29,
          "column": 35
        }
      }
    },
    {
      "type": {
        "label": ";",
        "beforeExpr": true,
        "startsExpr": false,
        "rightAssociative": false,
        "isLoop": false,
        "isAssign": false,
        "prefix": false,
        "postfix": false,
        "binop": null,
        "updateContext": null
      },
      "start": 430,
      "end": 431,
      "loc": {
        "start": {
          "line": 29,
          "column": 35
        },
        "end": {
          "line": 29,
          "column": 36
        }
      }
    },
    {
      "type": "CommentBlock",
      "value": "*\n * Default line height\n * @type {string}\n ",
      "start": 433,
      "end": 481,
      "loc": {
        "start": {
          "line": 31,
          "column": 0
        },
        "end": {
          "line": 34,
          "column": 3
        }
      }
    },
    {
      "type": {
        "label": "export",
        "keyword": "export",
        "beforeExpr": false,
        "startsExpr": false,
        "rightAssociative": false,
        "isLoop": false,
        "isAssign": false,
        "prefix": false,
        "postfix": false,
        "binop": null,
        "updateContext": null
      },
      "value": "export",
      "start": 482,
      "end": 488,
      "loc": {
        "start": {
          "line": 35,
          "column": 0
        },
        "end": {
          "line": 35,
          "column": 6
        }
      }
    },
    {
      "type": {
        "label": "const",
        "keyword": "const",
        "beforeExpr": false,
        "startsExpr": false,
        "rightAssociative": false,
        "isLoop": false,
        "isAssign": false,
        "prefix": false,
        "postfix": false,
        "binop": null,
        "updateContext": null
      },
      "value": "const",
      "start": 489,
      "end": 494,
      "loc": {
        "start": {
          "line": 35,
          "column": 7
        },
        "end": {
          "line": 35,
          "column": 12
        }
      }
    },
    {
      "type": {
        "label": "name",
        "beforeExpr": false,
        "startsExpr": true,
        "rightAssociative": false,
        "isLoop": false,
        "isAssign": false,
        "prefix": false,
        "postfix": false,
        "binop": null
      },
      "value": "LINE_HEIGHT",
      "start": 495,
      "end": 506,
      "loc": {
        "start": {
          "line": 35,
          "column": 13
        },
        "end": {
          "line": 35,
          "column": 24
        }
      }
    },
    {
      "type": {
        "label": "=",
        "beforeExpr": true,
        "startsExpr": false,
        "rightAssociative": false,
        "isLoop": false,
        "isAssign": true,
        "prefix": false,
        "postfix": false,
        "binop": null,
        "updateContext": null
      },
      "value": "=",
      "start": 507,
      "end": 508,
      "loc": {
        "start": {
          "line": 35,
          "column": 25
        },
        "end": {
          "line": 35,
          "column": 26
        }
      }
    },
    {
      "type": {
        "label": "string",
        "beforeExpr": false,
        "startsExpr": true,
        "rightAssociative": false,
        "isLoop": false,
        "isAssign": false,
        "prefix": false,
        "postfix": false,
        "binop": null,
        "updateContext": null
      },
      "value": "normal",
      "start": 509,
      "end": 517,
      "loc": {
        "start": {
          "line": 35,
          "column": 27
        },
        "end": {
          "line": 35,
          "column": 35
        }
      }
    },
    {
      "type": {
        "label": ";",
        "beforeExpr": true,
        "startsExpr": false,
        "rightAssociative": false,
        "isLoop": false,
        "isAssign": false,
        "prefix": false,
        "postfix": false,
        "binop": null,
        "updateContext": null
      },
      "start": 517,
      "end": 518,
      "loc": {
        "start": {
          "line": 35,
          "column": 35
        },
        "end": {
          "line": 35,
          "column": 36
        }
      }
    },
    {
      "type": "CommentBlock",
      "value": "*\n * Default text alignment\n * @type {string}\n ",
      "start": 520,
      "end": 571,
      "loc": {
        "start": {
          "line": 37,
          "column": 0
        },
        "end": {
          "line": 40,
          "column": 3
        }
      }
    },
    {
      "type": {
        "label": "export",
        "keyword": "export",
        "beforeExpr": false,
        "startsExpr": false,
        "rightAssociative": false,
        "isLoop": false,
        "isAssign": false,
        "prefix": false,
        "postfix": false,
        "binop": null,
        "updateContext": null
      },
      "value": "export",
      "start": 572,
      "end": 578,
      "loc": {
        "start": {
          "line": 41,
          "column": 0
        },
        "end": {
          "line": 41,
          "column": 6
        }
      }
    },
    {
      "type": {
        "label": "const",
        "keyword": "const",
        "beforeExpr": false,
        "startsExpr": false,
        "rightAssociative": false,
        "isLoop": false,
        "isAssign": false,
        "prefix": false,
        "postfix": false,
        "binop": null,
        "updateContext": null
      },
      "value": "const",
      "start": 579,
      "end": 584,
      "loc": {
        "start": {
          "line": 41,
          "column": 7
        },
        "end": {
          "line": 41,
          "column": 12
        }
      }
    },
    {
      "type": {
        "label": "name",
        "beforeExpr": false,
        "startsExpr": true,
        "rightAssociative": false,
        "isLoop": false,
        "isAssign": false,
        "prefix": false,
        "postfix": false,
        "binop": null
      },
      "value": "TEXT_ALIGN",
      "start": 585,
      "end": 595,
      "loc": {
        "start": {
          "line": 41,
          "column": 13
        },
        "end": {
          "line": 41,
          "column": 23
        }
      }
    },
    {
      "type": {
        "label": "=",
        "beforeExpr": true,
        "startsExpr": false,
        "rightAssociative": false,
        "isLoop": false,
        "isAssign": true,
        "prefix": false,
        "postfix": false,
        "binop": null,
        "updateContext": null
      },
      "value": "=",
      "start": 596,
      "end": 597,
      "loc": {
        "start": {
          "line": 41,
          "column": 24
        },
        "end": {
          "line": 41,
          "column": 25
        }
      }
    },
    {
      "type": {
        "label": "string",
        "beforeExpr": false,
        "startsExpr": true,
        "rightAssociative": false,
        "isLoop": false,
        "isAssign": false,
        "prefix": false,
        "postfix": false,
        "binop": null,
        "updateContext": null
      },
      "value": "start",
      "start": 598,
      "end": 605,
      "loc": {
        "start": {
          "line": 41,
          "column": 26
        },
        "end": {
          "line": 41,
          "column": 33
        }
      }
    },
    {
      "type": {
        "label": ";",
        "beforeExpr": true,
        "startsExpr": false,
        "rightAssociative": false,
        "isLoop": false,
        "isAssign": false,
        "prefix": false,
        "postfix": false,
        "binop": null,
        "updateContext": null
      },
      "start": 605,
      "end": 606,
      "loc": {
        "start": {
          "line": 41,
          "column": 33
        },
        "end": {
          "line": 41,
          "column": 34
        }
      }
    },
    {
      "type": "CommentBlock",
      "value": "*\n * Default text baseline\n * @type {string}\n ",
      "start": 608,
      "end": 658,
      "loc": {
        "start": {
          "line": 43,
          "column": 0
        },
        "end": {
          "line": 46,
          "column": 3
        }
      }
    },
    {
      "type": {
        "label": "export",
        "keyword": "export",
        "beforeExpr": false,
        "startsExpr": false,
        "rightAssociative": false,
        "isLoop": false,
        "isAssign": false,
        "prefix": false,
        "postfix": false,
        "binop": null,
        "updateContext": null
      },
      "value": "export",
      "start": 659,
      "end": 665,
      "loc": {
        "start": {
          "line": 47,
          "column": 0
        },
        "end": {
          "line": 47,
          "column": 6
        }
      }
    },
    {
      "type": {
        "label": "const",
        "keyword": "const",
        "beforeExpr": false,
        "startsExpr": false,
        "rightAssociative": false,
        "isLoop": false,
        "isAssign": false,
        "prefix": false,
        "postfix": false,
        "binop": null,
        "updateContext": null
      },
      "value": "const",
      "start": 666,
      "end": 671,
      "loc": {
        "start": {
          "line": 47,
          "column": 7
        },
        "end": {
          "line": 47,
          "column": 12
        }
      }
    },
    {
      "type": {
        "label": "name",
        "beforeExpr": false,
        "startsExpr": true,
        "rightAssociative": false,
        "isLoop": false,
        "isAssign": false,
        "prefix": false,
        "postfix": false,
        "binop": null
      },
      "value": "TEXT_BASELINE",
      "start": 672,
      "end": 685,
      "loc": {
        "start": {
          "line": 47,
          "column": 13
        },
        "end": {
          "line": 47,
          "column": 26
        }
      }
    },
    {
      "type": {
        "label": "=",
        "beforeExpr": true,
        "startsExpr": false,
        "rightAssociative": false,
        "isLoop": false,
        "isAssign": true,
        "prefix": false,
        "postfix": false,
        "binop": null,
        "updateContext": null
      },
      "value": "=",
      "start": 686,
      "end": 687,
      "loc": {
        "start": {
          "line": 47,
          "column": 27
        },
        "end": {
          "line": 47,
          "column": 28
        }
      }
    },
    {
      "type": {
        "label": "string",
        "beforeExpr": false,
        "startsExpr": true,
        "rightAssociative": false,
        "isLoop": false,
        "isAssign": false,
        "prefix": false,
        "postfix": false,
        "binop": null,
        "updateContext": null
      },
      "value": "alphabetic",
      "start": 688,
      "end": 700,
      "loc": {
        "start": {
          "line": 47,
          "column": 29
        },
        "end": {
          "line": 47,
          "column": 41
        }
      }
    },
    {
      "type": {
        "label": ";",
        "beforeExpr": true,
        "startsExpr": false,
        "rightAssociative": false,
        "isLoop": false,
        "isAssign": false,
        "prefix": false,
        "postfix": false,
        "binop": null,
        "updateContext": null
      },
      "start": 700,
      "end": 701,
      "loc": {
        "start": {
          "line": 47,
          "column": 41
        },
        "end": {
          "line": 47,
          "column": 42
        }
      }
    },
    {
      "type": {
        "label": "eof",
        "beforeExpr": false,
        "startsExpr": false,
        "rightAssociative": false,
        "isLoop": false,
        "isAssign": false,
        "prefix": false,
        "postfix": false,
        "binop": null,
        "updateContext": null
      },
      "start": 702,
      "end": 702,
      "loc": {
        "start": {
          "line": 48,
          "column": 0
        },
        "end": {
          "line": 48,
          "column": 0
        }
      }
    }
  ]
}